{
  "brand": "Dot & Key",
  "collection_date": "2026-03-08T22:49:15.480553",
  "source": "automated_scraping",
  "country": "IN",
  "ads": [
    {
      "ad_id": "scraped--1869121378547995486",
      "page_name": "Unlock Clear, Radiant Skin with Dot & Key's Cica & Niacinamide Essentials\ud83e\udd29",
      "ad_text": "Unlock Clear, Radiant Skin with Dot & Key's Cica & Niacinamide Essentials\ud83e\udd29 \ud83d\udc9a Cica & 2% Salicylic Face Wash - Stabilizes skin\u2019s sebum production \ud83d\udc9a CICA + Niacinamide Oil - Free Moisturizer - Fights acne & acne scars",
      "start_date": null,
      "stop_date": null,
      "platforms": [],
      "is_active": true,
      "creative_type": "image",
      "scraped_at": "2026-03-08T22:46:23.080163"
    },
    {
      "ad_id": "scraped--4270811489712701728",
      "page_name": "Keep the Glow Going All Summer Long with Dot & Key\u2019s Moisturizers \ud83c\udf1e\ud83d\udc96",
      "ad_text": "Keep the Glow Going All Summer Long with Dot & Key\u2019s Moisturizers \ud83c\udf1e\ud83d\udc96 \ud83e\udd29 Vitamin C - Glowing skin \ud83e\udd29 Barrier Repair - Deep Moisturized Skin",
      "start_date": null,
      "stop_date": null,
      "platforms": [],
      "is_active": true,
      "creative_type": "image",
      "scraped_at": "2026-03-08T22:46:26.193115"
    },
    {
      "ad_id": "scraped--33757727195098002",
      "page_name": "Skincare that feels good! Try Dot & Key",
      "ad_text": "Skincare that feels good! Try Dot & Key \u2714 Fruits made clinically effective",
      "start_date": null,
      "stop_date": null,
      "platforms": [],
      "is_active": true,
      "creative_type": "image",
      "scraped_at": "2026-03-08T22:46:32.526443"
    },
    {
      "ad_id": "scraped-1925039839406126833",
      "page_name": "Brands like Bombay Shaving Company, Mokobara, Dot & Key, achieved:",
      "ad_text": "Brands like Bombay Shaving Company, Mokobara, Dot & Key, achieved: - 90%+ delivery rates Join 3000+ brands using BiteSpeed's AI-native retention platform",
      "start_date": null,
      "stop_date": null,
      "platforms": [],
      "is_active": true,
      "creative_type": "image",
      "scraped_at": "2026-03-08T22:46:38.981061"
    },
    {
      "ad_id": "scraped-4123130977201027996",
      "page_name": "The Dot & Key faves in your cart are selling fast!",
      "ad_text": "The Dot & Key faves in your cart are selling fast! Grab them now & step into your glow-up era with skincare that feels good.",
      "start_date": null,
      "stop_date": null,
      "platforms": [],
      "is_active": true,
      "creative_type": "image",
      "scraped_at": "2026-03-08T22:47:18.365454"
    },
    {
      "ad_id": "scraped-1300424608721327196",
      "page_name": "\"Skincare should make sense and it should feel good.\" \u2014 Anisha Saraf, Founder of Dot & Key Skincare.",
      "ad_text": "\"Skincare should make sense and it should feel good.\" \u2014 Anisha Saraf, Founder of Dot & Key Skincare. We believe your daily SPF should be as reliable as it is comfortable. That\u2019s why all our sunscreens are In-Vivo Tested.",
      "start_date": null,
      "stop_date": null,
      "platforms": [],
      "is_active": true,
      "creative_type": "image",
      "scraped_at": "2026-03-08T22:47:28.699948"
    },
    {
      "ad_id": "scraped-3370798854891455616",
      "page_name": "Get Even Toned, Glowing Skin with 10% Vitamin C Serum \ud83e\udd29 \u2705 Brightens complexion\u2705 Treats Pigmentation & Dark spotsWhy Dot & Key?\u2714\ufe0f Clinically Proven Results \u2714\ufe0f Dermatologically Tested\u2714\ufe0f Uncompromised Efficacy\u2714\ufe0f No Nasties\u2714\ufe0f Cruelty-Free",
      "ad_text": "Get Even Toned, Glowing Skin with 10% Vitamin C Serum \ud83e\udd29 \u2705 Brightens complexion\u2705 Treats Pigmentation & Dark spotsWhy Dot & Key?\u2714\ufe0f Clinically Proven Results \u2714\ufe0f Dermatologically Tested\u2714\ufe0f Uncompromised Efficacy\u2714\ufe0f No Nasties\u2714\ufe0f Cruelty-Free",
      "start_date": null,
      "stop_date": null,
      "platforms": [],
      "is_active": true,
      "creative_type": "image",
      "scraped_at": "2026-03-08T22:49:11.306268"
    }
  ]
}